filepack/__init__.py
filepack/archive.py
filepack/compression.py
filepack/consts.py
filepack/exceptions.py
filepack/filepack.py
filepack/utils.py
filepack/archives/consts.py
filepack/archives/exceptions.py
filepack/archives/models.py
filepack/archives/rar.py
filepack/archives/seven_zip.py
filepack/archives/tar.py
filepack/archives/zip.py
filepack/compressions/bzip2.py
filepack/compressions/consts.py
filepack/compressions/exceptions.py
filepack/compressions/gzip.py
filepack/compressions/lz4.py
filepack/compressions/models.py
filepack/compressions/xz.py
filepack-0.1.0.dist-info/LICENSE
filepack-0.1.0.dist-info/METADATA
filepack-0.1.0.dist-info/WHEEL
filepack-0.1.0.dist-info/entry_points.txt
filepack-0.1.0.dist-info/top_level.txt
filepack-0.1.0.dist-info/RECORD
