Metadata-Version: 2.1
Name: filepack
Version: 0.1.0
Summary: A user-friendly interface for handling files, archives, and compressed files in Python
Author-email: Dan Manor <danmanor11@gmail.com>
License: MIT License
Project-URL: Repository, https://github.com/danmanor/filepack
Project-URL: Bug Tracker, https://github.com/danmanor/filepack/issues
Keywords: file,pack,unpack,archive,compression,compressor
Classifier: Development Status :: 3 - Alpha
Classifier: License :: OSI Approved :: MIT License
Classifier: Programming Language :: Python :: 3.12
Requires-Python: >=3.12.0
License-File: LICENSE
Requires-Dist: py7zr >=0.20.6
Requires-Dist: tabulate ==0.9.0
Requires-Dist: types-tabulate ==0.9.0.3
Requires-Dist: rarfile ==4.1
Requires-Dist: pytz ==2023.3.post1
Requires-Dist: types-pytz ==2023.3.1.1
Requires-Dist: lz4 ==4.3.2
Requires-Dist: filetype ==1.2.0
Requires-Dist: docopt ==0.6.2
Requires-Dist: toml ==0.10.2
Provides-Extra: format
Requires-Dist: black ==23.9.1 ; extra == 'format'
Requires-Dist: isort ==5.12.0 ; extra == 'format'
Provides-Extra: lint
Requires-Dist: flake8 ==6.1.0 ; extra == 'lint'
Provides-Extra: test
Requires-Dist: pytest ==7.4.2 ; extra == 'test'
Provides-Extra: test-runner
Requires-Dist: tox ==4.11.3 ; extra == 'test-runner'
Provides-Extra: types
Requires-Dist: mypy ==1.5.1 ; extra == 'types'
